[
    {
        "original": "0/114/117/342/30023357310125/atlas.webp",
        "Grass Tiles": {
            "dark_gravel": {
                "height": 128,
                "width": 128,
                "x": 3936,
                "y": 3936
            },
            "dd_cor_1": {
                "height": 128,
                "width": 128,
                "x": 3936,
                "y": 3744
            },
            "dd_tr_4": {
                "height": 128,
                "width": 128,
                "x": 3872,
                "y": 2656
            },
            "dg_cor_1": {
                "height": 128,
                "width": 128,
                "x": 3872,
                "y": 2464
            },
            "dg_cor_2": {
                "height": 128,
                "width": 128,
                "x": 3552,
                "y": 2144
            },
            "dg_cor_3": {
                "height": 128,
                "width": 128,
                "x": 2592,
                "y": 1248
            },
            "dg_cor_4": {
                "height": 128,
                "width": 128,
                "x": 3872,
                "y": 2272
            },
            "dg_incor_1": {
                "height": 128,
                "width": 128,
                "x": 2336,
                "y": 920
            },
            "dg_incor_2": {
                "height": 128,
                "width": 128,
                "x": 2569,
                "y": 1056
            },
            "dg_tr_1": {
                "height": 128,
                "width": 128,
                "x": 2528,
                "y": 864
            },
            "dg_tr_2": {
                "height": 128,
                "width": 128,
                "x": 3232,
                "y": 1663
            },
            "dg_tr_3": {
                "height": 128,
                "width": 128,
                "x": 3232,
                "y": 1471
            },
            "dd_cor_2": {
                "height": 128,
                "width": 128,
                "x": 3936,
                "y": 3552
            },
            "dg_tr_4": {
                "height": 128,
                "width": 128,
                "x": 3232,
                "y": 1279
            },
            "grass_1": {
                "height": 128,
                "width": 128,
                "x": 2144,
                "y": 800
            },
            "grass_2": {
                "height": 128,
                "width": 128,
                "x": 2336,
                "y": 728
            },
            "grass_3": {
                "height": 128,
                "width": 128,
                "x": 2144,
                "y": 608
            },
            "grass_4": {
                "height": 128,
                "width": 128,
                "x": 2144,
                "y": 416
            },
            "grass_railroad": {
                "height": 128,
                "width": 128,
                "x": 2336,
                "y": 536
            },
            "gravel": {
                "height": 128,
                "width": 128,
                "x": 2528,
                "y": 672
            },
            "grass3_1_1": {
                "height": 128,
                "width": 384,
                "x": 32,
                "y": 96
            },
            "grass3_1_2": {
                "height": 128,
                "width": 384,
                "x": 1184,
                "y": 672
            },
            "grass2_2_1": {
                "height": 256,
                "width": 256,
                "x": 2656,
                "y": 3232
            },
            "dd_cor_3": {
                "height": 128,
                "width": 128,
                "x": 3936,
                "y": 3360
            },
            "grass2_2_2": {
                "height": 256,
                "width": 256,
                "x": 1184,
                "y": 352
            },
            "grass2_2_3": {
                "height": 256,
                "width": 256,
                "x": 1184,
                "y": 32
            },
            "grass2_2_4": {
                "height": 256,
                "width": 256,
                "x": 2976,
                "y": 3232
            },
            "grass2_2_5": {
                "height": 256,
                "width": 256,
                "x": 3296,
                "y": 3232
            },
            "grass2_1_1": {
                "height": 128,
                "width": 256,
                "x": 2272,
                "y": 1312
            },
            "grass2_1_2": {
                "height": 128,
                "width": 256,
                "x": 3232,
                "y": 2208
            },
            "dd_cor_4": {
                "height": 128,
                "width": 128,
                "x": 928,
                "y": 96
            },
            "dd_incor_1": {
                "height": 128,
                "width": 128,
                "x": 3208,
                "y": 1855
            },
            "dd_incor_2": {
                "height": 128,
                "width": 128,
                "x": 1952,
                "y": 480
            },
            "dd_tr_1": {
                "height": 128,
                "width": 128,
                "x": 1952,
                "y": 288
            },
            "dd_tr_2": {
                "height": 128,
                "width": 128,
                "x": 1952,
                "y": 96
            },
            "dd_tr_3": {
                "height": 128,
                "width": 128,
                "x": 3872,
                "y": 2848
            }
        },
        "Concrete Walls": {
            "wall_e3_g": {
                "height": 256,
                "width": 256,
                "x": 2592,
                "y": 1440
            },
            "wall_e2": {
                "height": 256,
                "width": 256,
                "x": 2592,
                "y": 2400
            },
            "wall_e2_g": {
                "height": 256,
                "width": 256,
                "x": 2912,
                "y": 2720
            },
            "wall_st": {
                "height": 256,
                "width": 256,
                "x": 2592,
                "y": 2080
            },
            "wall_st_g": {
                "height": 256,
                "width": 256,
                "x": 2912,
                "y": 2400
            },
            "wall_e1": {
                "height": 256,
                "width": 256,
                "x": 3232,
                "y": 2720
            },
            "wall_e1_g": {
                "height": 256,
                "width": 256,
                "x": 2592,
                "y": 1760
            },
            "wall_cr": {
                "height": 256,
                "width": 256,
                "x": 2912,
                "y": 2080
            },
            "wall_cr_g": {
                "height": 256,
                "width": 256,
                "x": 3232,
                "y": 2400
            },
            "wall_e3": {
                "height": 256,
                "width": 256,
                "x": 3552,
                "y": 2720
            }
        },
        "Small Bridge": {
            "sm_br_1": {
                "height": 1024,
                "width": 1024,
                "x": 32,
                "y": 3040
            },
            "sm_br_1_gr": {
                "height": 1024,
                "width": 1024,
                "x": 32,
                "y": 1952
            }
        },
        "NuBu 9": {
            "nubu_9": {
                "height": 512,
                "width": 512,
                "x": 1120,
                "y": 1312
            }
        },
        "City Builds": {
            "fab_tow2": {
                "height": 512,
                "width": 512,
                "x": 3360,
                "y": 3552
            },
            "fab_tow": {
                "height": 512,
                "width": 512,
                "x": 1696,
                "y": 2464
            }
        },
        "Promotion": {
            "shit_0": {
                "height": 512,
                "width": 512,
                "x": 1696,
                "y": 1888
            }
        },
        "NuBu 4": {
            "nubu_4": {
                "height": 1024,
                "width": 1024,
                "x": 1120,
                "y": 3040
            }
        },
        "NuBu 12": {
            "nubu_12": {
                "height": 1024,
                "width": 1024,
                "x": 32,
                "y": 864
            }
        },
        "Bush 3D": {
            "bush2": {
                "height": 512,
                "width": 512,
                "x": 1696,
                "y": 1312
            },
            "bush1": {
                "height": 512,
                "width": 512,
                "x": 608,
                "y": 288
            }
        },
        "Concrete Tiles": {
            "pave_1": {
                "height": 128,
                "width": 128,
                "x": 2144,
                "y": 224
            },
            "pave_2": {
                "height": 128,
                "width": 128,
                "x": 2144,
                "y": 32
            },
            "pave_3": {
                "height": 128,
                "width": 128,
                "x": 2336,
                "y": 344
            },
            "pave_4": {
                "height": 128,
                "width": 128,
                "x": 2528,
                "y": 480
            },
            "pg_corner_1": {
                "height": 128,
                "width": 128,
                "x": 2336,
                "y": 152
            },
            "pg_corner_2": {
                "height": 128,
                "width": 128,
                "x": 2528,
                "y": 288
            },
            "pg_incor_1": {
                "height": 128,
                "width": 128,
                "x": 2528,
                "y": 96
            },
            "pg_trans_1": {
                "height": 128,
                "width": 128,
                "x": 3400,
                "y": 1855
            },
            "pg_trans_2": {
                "height": 128,
                "width": 128,
                "x": 3424,
                "y": 1663
            },
            "pg_trans_3": {
                "height": 128,
                "width": 128,
                "x": 3424,
                "y": 1471
            },
            "fliptile": {
                "height": 128,
                "width": 128,
                "x": 3424,
                "y": 1279
            },
            "concrete_road": {
                "height": 128,
                "width": 384,
                "x": 480,
                "y": 96
            },
            "concrete_road_0": {
                "height": 128,
                "width": 384,
                "x": 1632,
                "y": 672
            },
            "concrete_road_det_1": {
                "height": 128,
                "width": 384,
                "x": 1504,
                "y": 480
            },
            "concrete_road_det_2": {
                "height": 128,
                "width": 384,
                "x": 1504,
                "y": 288
            },
            "concrete_road_det_3": {
                "height": 128,
                "width": 384,
                "x": 1504,
                "y": 96
            },
            "concrete_road_end": {
                "height": 128,
                "width": 384,
                "x": 2656,
                "y": 3040
            },
            "concrete_road_end_zebra": {
                "height": 128,
                "width": 384,
                "x": 3104,
                "y": 3040
            },
            "concrete_road_zebra": {
                "height": 128,
                "width": 384,
                "x": 3552,
                "y": 3040
            },
            "concrete_1": {
                "height": 128,
                "width": 128,
                "x": 3592,
                "y": 1952
            },
            "concrete_2": {
                "height": 128,
                "width": 128,
                "x": 3616,
                "y": 1760
            },
            "concrete_3": {
                "height": 128,
                "width": 128,
                "x": 3616,
                "y": 1568
            },
            "concrete_4": {
                "height": 128,
                "width": 128,
                "x": 3616,
                "y": 1376
            },
            "pc_corner_1": {
                "height": 128,
                "width": 128,
                "x": 3616,
                "y": 1184
            },
            "pc_corner_2": {
                "height": 128,
                "width": 128,
                "x": 2720,
                "y": 864
            },
            "pc_incor_1": {
                "height": 128,
                "width": 128,
                "x": 2720,
                "y": 672
            },
            "pc_trans_1": {
                "height": 128,
                "width": 128,
                "x": 2720,
                "y": 480
            },
            "pc_trans_2": {
                "height": 128,
                "width": 128,
                "x": 2720,
                "y": 288
            },
            "pc_trans_3": {
                "height": 128,
                "width": 128,
                "x": 2720,
                "y": 96
            },
            "pc_turn": {
                "height": 256,
                "width": 256,
                "x": 3616,
                "y": 3232
            },
            "pc_turn_2": {
                "height": 256,
                "width": 256,
                "x": 2016,
                "y": 992
            },
            "pavement_2x1_1": {
                "height": 128,
                "width": 256,
                "x": 3552,
                "y": 2528
            },
            "pavement_2x1_2": {
                "height": 128,
                "width": 256,
                "x": 3552,
                "y": 2336
            },
            "pavement_2x1_3": {
                "height": 128,
                "width": 256,
                "x": 2912,
                "y": 1569
            },
            "pavement_2x1_4": {
                "height": 128,
                "width": 256,
                "x": 2912,
                "y": 1377
            },
            "pavement_2x2_1": {
                "height": 256,
                "width": 256,
                "x": 2272,
                "y": 2784
            },
            "pavement_2x2_2": {
                "height": 256,
                "width": 256,
                "x": 2272,
                "y": 2464
            },
            "pc_3turn": {
                "height": 384,
                "width": 384,
                "x": 1120,
                "y": 864
            },
            "pavement_3x3_1": {
                "height": 384,
                "width": 384,
                "x": 2208,
                "y": 3104
            },
            "pavement_3x3_2": {
                "height": 384,
                "width": 384,
                "x": 1568,
                "y": 864
            }
        },
        "Cliffs": {
            "cliff_c2": {
                "height": 256,
                "width": 256,
                "x": 2272,
                "y": 2144
            },
            "cliff_0": {
                "height": 256,
                "width": 256,
                "x": 2272,
                "y": 1824
            },
            "cliff_1": {
                "height": 256,
                "width": 256,
                "x": 2272,
                "y": 1504
            },
            "cliff_co": {
                "height": 256,
                "width": 256,
                "x": 2592,
                "y": 2720
            },
            "cliff_ri": {
                "height": 512,
                "width": 512,
                "x": 1120,
                "y": 2464
            }
        },
        "Bush": {
            "wood1": {
                "height": 255,
                "width": 232,
                "x": 2912,
                "y": 1761
            },
            "bush1": {
                "height": 136,
                "width": 169,
                "x": 2336,
                "y": 1112
            },
            "bush2": {
                "height": 97,
                "width": 132,
                "x": 3232,
                "y": 2047
            }
        },
        "Village Builds": {
            "vilhou2": {
                "height": 512,
                "width": 512,
                "x": 2208,
                "y": 3552
            },
            "vilhou1": {
                "height": 512,
                "width": 512,
                "x": 32,
                "y": 288
            }
        },
        "Slopes Rises": {
            "grass": {
                "height": 128,
                "width": 128,
                "x": 2761,
                "y": 1056
            },
            "slope_1": {
                "height": 128,
                "width": 128,
                "x": 2953,
                "y": 1185
            },
            "slope_2": {
                "height": 128,
                "width": 128,
                "x": 2953,
                "y": 993
            },
            "rise_3": {
                "height": 512,
                "width": 512,
                "x": 1120,
                "y": 1888
            },
            "rise_2": {
                "height": 512,
                "width": 512,
                "x": 2784,
                "y": 3552
            }
        }
    }
]