[
    {
        "original": "0/16716/133/31/30023247324016/atlas.webp",
        "Land Rocks Winter": {
            "bg_rock1": {
                "height": 256,
                "width": 256,
                "x": 32,
                "y": 32
            },
            "bg_rock2": {
                "height": 256,
                "width": 256,
                "x": 352,
                "y": 32
            },
            "corn4": {
                "height": 512,
                "width": 512,
                "x": 32,
                "y": 352
            },
            "rise_r1": {
                "height": 512,
                "width": 512,
                "x": 608,
                "y": 928
            },
            "sm_rck1": {
                "height": 256,
                "width": 256,
                "x": 1184,
                "y": 864
            },
            "sm_rck2": {
                "height": 256,
                "width": 256,
                "x": 2400,
                "y": 1760
            },
            "sm_rck3": {
                "height": 256,
                "width": 256,
                "x": 1184,
                "y": 544
            },
            "sm_rck4": {
                "height": 256,
                "width": 256,
                "x": 2720,
                "y": 1760
            },
            "bg_rock3": {
                "height": 256,
                "width": 256,
                "x": 672,
                "y": 32
            },
            "bg_rock4": {
                "height": 256,
                "width": 256,
                "x": 992,
                "y": 32
            },
            "rise_u1": {
                "height": 256,
                "width": 256,
                "x": 1760,
                "y": 1760
            },
            "rise_u2": {
                "height": 256,
                "width": 256,
                "x": 1184,
                "y": 1184
            },
            "rise_u3": {
                "height": 256,
                "width": 256,
                "x": 2080,
                "y": 1760
            },
            "corn1": {
                "height": 512,
                "width": 512,
                "x": 32,
                "y": 1504
            },
            "corn2": {
                "height": 512,
                "width": 512,
                "x": 32,
                "y": 928
            },
            "corn3": {
                "height": 512,
                "width": 512,
                "x": 608,
                "y": 1504
            }
        },
        "Bush Winter": {
            "bush1": {
                "height": 130,
                "width": 169,
                "x": 1760,
                "y": 1566
            },
            "bush2": {
                "height": 124,
                "width": 122,
                "x": 1696,
                "y": 610
            },
            "wood1": {
                "height": 256,
                "width": 145,
                "x": 1504,
                "y": 1184
            }
        },
        "Land Tiles Winter": {
            "asp_1": {
                "height": 128,
                "width": 128,
                "x": 1184,
                "y": 352
            },
            "asp_11": {
                "height": 128,
                "width": 128,
                "x": 3040,
                "y": 1888
            },
            "asp_12": {
                "height": 128,
                "width": 128,
                "x": 1504,
                "y": 992
            },
            "asp_14": {
                "height": 128,
                "width": 128,
                "x": 1993,
                "y": 1568
            },
            "asp_2": {
                "height": 128,
                "width": 128,
                "x": 3232,
                "y": 1888
            },
            "asp_3": {
                "height": 128,
                "width": 128,
                "x": 1504,
                "y": 800
            },
            "asp_4": {
                "height": 128,
                "width": 128,
                "x": 2185,
                "y": 1568
            },
            "asp_5": {
                "height": 128,
                "width": 128,
                "x": 3424,
                "y": 1888
            },
            "asp_6": {
                "height": 128,
                "width": 128,
                "x": 1504,
                "y": 608
            },
            "asp_7": {
                "height": 128,
                "width": 128,
                "x": 2377,
                "y": 1568
            },
            "asp_8": {
                "height": 128,
                "width": 128,
                "x": 3616,
                "y": 1888
            },
            "asp_9": {
                "height": 128,
                "width": 128,
                "x": 2569,
                "y": 1568
            },
            "beton_1": {
                "height": 128,
                "width": 128,
                "x": 3808,
                "y": 1888
            },
            "beton_2": {
                "height": 128,
                "width": 128,
                "x": 2761,
                "y": 1568
            },
            "beton_3": {
                "height": 128,
                "width": 128,
                "x": 1376,
                "y": 352
            },
            "beton_4": {
                "height": 128,
                "width": 128,
                "x": 1312,
                "y": 160
            },
            "beton_5": {
                "height": 128,
                "width": 128,
                "x": 3040,
                "y": 1696
            },
            "beton_6": {
                "height": 128,
                "width": 128,
                "x": 3232,
                "y": 1696
            },
            "beton_7": {
                "height": 100,
                "width": 100,
                "x": 1882,
                "y": 634
            },
            "beton_tube": {
                "height": 128,
                "width": 128,
                "x": 3424,
                "y": 1696
            },
            "dirt_1": {
                "height": 128,
                "width": 128,
                "x": 3616,
                "y": 1696
            },
            "dirt_2": {
                "height": 128,
                "width": 128,
                "x": 3808,
                "y": 1696
            },
            "dirt_3": {
                "height": 128,
                "width": 128,
                "x": 1568,
                "y": 416
            },
            "dirt_4": {
                "height": 128,
                "width": 128,
                "x": 1504,
                "y": 160
            },
            "dirt_5": {
                "height": 128,
                "width": 128,
                "x": 1760,
                "y": 1374
            },
            "dirt_8": {
                "height": 128,
                "width": 128,
                "x": 1713,
                "y": 1182
            },
            "dirt_9": {
                "height": 128,
                "width": 128,
                "x": 1696,
                "y": 990
            },
            "grass_a1": {
                "height": 128,
                "width": 128,
                "x": 1696,
                "y": 798
            },
            "grass_a2": {
                "height": 128,
                "width": 128,
                "x": 1760,
                "y": 418
            },
            "grass_a3": {
                "height": 128,
                "width": 128,
                "x": 1905,
                "y": 1182
            },
            "grass_a4": {
                "height": 128,
                "width": 128,
                "x": 1888,
                "y": 990
            },
            "grass_b1": {
                "height": 128,
                "width": 128,
                "x": 1888,
                "y": 798
            },
            "grass_b2": {
                "height": 128,
                "width": 128,
                "x": 1952,
                "y": 1374
            },
            "grass_b3": {
                "height": 128,
                "width": 128,
                "x": 2144,
                "y": 1376
            },
            "grass_b4": {
                "height": 128,
                "width": 128,
                "x": 2336,
                "y": 1376
            },
            "rail_1": {
                "height": 128,
                "width": 128,
                "x": 2528,
                "y": 1376
            },
            "rail_2": {
                "height": 128,
                "width": 128,
                "x": 2720,
                "y": 1376
            },
            "road_1": {
                "height": 128,
                "width": 128,
                "x": 1952,
                "y": 442
            },
            "road_2": {
                "height": 128,
                "width": 128,
                "x": 2097,
                "y": 1182
            },
            "road_3": {
                "height": 128,
                "width": 128,
                "x": 2080,
                "y": 990
            },
            "road_4": {
                "height": 128,
                "width": 128,
                "x": 2080,
                "y": 798
            },
            "road_6": {
                "height": 128,
                "width": 128,
                "x": 2289,
                "y": 1184
            },
            "road_8": {
                "height": 128,
                "width": 128,
                "x": 2481,
                "y": 1184
            },
            "road_9": {
                "height": 128,
                "width": 128,
                "x": 2673,
                "y": 1184
            },
            "sand_1": {
                "height": 128,
                "width": 128,
                "x": 2865,
                "y": 1184
            },
            "sand_2": {
                "height": 128,
                "width": 128,
                "x": 2912,
                "y": 1376
            },
            "sand_3": {
                "height": 128,
                "width": 128,
                "x": 3104,
                "y": 1504
            }
        },
        "Promotion Winter": {
            "shit_0": {
                "height": 512,
                "width": 512,
                "x": 1184,
                "y": 1504
            }
        },
        "Bush Winter 3D": {
            "bush3": {
                "height": 512,
                "width": 512,
                "x": 608,
                "y": 352
            }
        }
    }
]